hnbex/__init__.py
hnbex/__main__.py
hnbex/api.py
hnbex/commands.py
hnbex/console.py
hnbex/output.py
hnbex/templates/dumb.gnuplot
hnbex/templates/qt.gnuplot
hnbex_cli-2.1.0.dist-info/LICENSE
hnbex_cli-2.1.0.dist-info/METADATA
hnbex_cli-2.1.0.dist-info/WHEEL
hnbex_cli-2.1.0.dist-info/entry_points.txt
hnbex_cli-2.1.0.dist-info/top_level.txt
hnbex_cli-2.1.0.dist-info/RECORD
