Metadata-Version: 2.1
Name: hnbex-cli
Version: 2.1.0
Summary: CLI tool for displaying exchange rates for Croatian Kuna
Author-email: Ivan Habunek <ivan@habunek.com>
License: GNU GENERAL PUBLIC LICENSE
Project-URL: Homepage, https://github.com/ihabunek/hnbex-cli
Project-URL: Issues, https://github.com/ihabunek/hnbex-cli/issues
Keywords: hnb,exchange,rate,currency
Classifier: Environment :: Console
Classifier: License :: OSI Approved :: GNU General Public License v3 (GPLv3)
Classifier: Operating System :: OS Independent
Classifier: Programming Language :: Python :: 3
Requires-Python: >=3.7
License-File: LICENSE
Provides-Extra: dev
Requires-Dist: build ; extra == 'dev'
Requires-Dist: twine ; extra == 'dev'
